getcp/__init__.py
getcp/cc.py
getcp/cf.py
getcp/github.py
getcp-1.0.24.dist-info/LICENSE
getcp-1.0.24.dist-info/METADATA
getcp-1.0.24.dist-info/WHEEL
getcp-1.0.24.dist-info/top_level.txt
getcp-1.0.24.dist-info/RECORD
